xNormal.py
xNormal-1.1.1.dist-info/LICENSE.md
xNormal-1.1.1.dist-info/METADATA
xNormal-1.1.1.dist-info/WHEEL
xNormal-1.1.1.dist-info/top_level.txt
xNormal-1.1.1.dist-info/RECORD
