Metadata-Version: 2.1
Name: xNormal
Version: 1.1.1
Summary: Wrapper for xNormal
Home-page: https://github.com/orangeduck/Python-xNormal
Author: Daniel Holden, Paul Greveson
Author-email: contact@theorangeduck.com
License: UNKNOWN
Platform: UNKNOWN
